unfccc_di_api/__init__.py
unfccc_di_api/unfccc_di_api.py
unfccc_di_api/tests/__init__.py
unfccc_di_api/tests/test_unfccc_di_api.py
unfccc_di_api-4.0.4.dist-info/LICENSE
unfccc_di_api-4.0.4.dist-info/METADATA
unfccc_di_api-4.0.4.dist-info/WHEEL
unfccc_di_api-4.0.4.dist-info/top_level.txt
unfccc_di_api-4.0.4.dist-info/RECORD
