Metadata-Version: 2.1
Name: unfccc_di_api
Version: 4.0.4
Summary: Python wrapper around the Flexible Query API of the UNFCCC.
Home-page: https://github.com/pik-primap/unfccc_di_api
Author: Mika Pflüger
Author-email: mika.pflueger@pik-potsdam.de
License: Apache Software License 2.0
Project-URL: Documentation, https://unfccc-di-api.readthedocs.io
Classifier: Development Status :: 5 - Production/Stable
Classifier: Intended Audience :: Science/Research
Classifier: Topic :: Scientific/Engineering :: Atmospheric Science
Classifier: License :: OSI Approved :: Apache Software License
Classifier: Natural Language :: English
Classifier: Programming Language :: Python :: 3
Classifier: Programming Language :: Python :: 3.9
Classifier: Programming Language :: Python :: 3.10
Classifier: Programming Language :: Python :: 3.11
Classifier: Programming Language :: Python :: 3.12
Requires-Python: >=3.9
License-File: LICENSE
Requires-Dist: pandas
Requires-Dist: treelib
Requires-Dist: requests
Requires-Dist: pooch >=1.8.0
Requires-Dist: fake-useragent
Requires-Dist: pyarrow
Provides-Extra: dev
Requires-Dist: pip ; extra == 'dev'
Requires-Dist: wheel ; extra == 'dev'
Requires-Dist: build ; extra == 'dev'
Requires-Dist: watchdog ; extra == 'dev'
Requires-Dist: flake8 ; extra == 'dev'
Requires-Dist: coverage ; extra == 'dev'
Requires-Dist: Sphinx >=6 ; extra == 'dev'
Requires-Dist: twine ; extra == 'dev'
Requires-Dist: pytest ; extra == 'dev'
Requires-Dist: pytest-runner ; extra == 'dev'
Requires-Dist: pre-commit ; extra == 'dev'
Requires-Dist: sphinx-rtd-theme ; extra == 'dev'
Requires-Dist: ipykernel ; extra == 'dev'
Requires-Dist: nbsphinx ; extra == 'dev'
Requires-Dist: tbump ; extra == 'dev'
Requires-Dist: tox ; extra == 'dev'
Provides-Extra: test
Requires-Dist: pytest ; extra == 'test'
